iqa/__init__.py
iqa/metrics/__init__.py
iqa/metrics/fid.py
iqa/metrics/niqe.py
iqa/metrics/psnr.py
iqa/metrics/ssim.py
iqa/models/__init__.py
iqa/models/inceptionv3.py
iqa/utils/__init__.py
iqa/utils/convert_img.py
iqa_jax-0.0.1.dist-info/LICENSE
iqa_jax-0.0.1.dist-info/METADATA
iqa_jax-0.0.1.dist-info/WHEEL
iqa_jax-0.0.1.dist-info/top_level.txt
iqa_jax-0.0.1.dist-info/RECORD
