Metadata-Version: 2.1
Name: iqa-jax
Version: 0.0.1
Summary: IQA library for Jax
Home-page: https://github.com/dslisleedh/IQA-jax
Author: dslisleedh
Author-email: dslisleedh@gmail.com
Project-URL: Bug Tracker, https://github.com/dslisleedh/IQA-jax/issues
Classifier: Programming Language :: Python :: 3
Classifier: License :: OSI Approved :: Apache Software License
Classifier: Intended Audience :: Developers
Classifier: Intended Audience :: Science/Research
Classifier: Topic :: Scientific/Engineering :: Image Processing
Requires-Python: >=3.6
License-File: LICENSE
Requires-Dist: numpy (>=1.12)
Requires-Dist: jax (>=0.4.2)
Requires-Dist: tensorflow (>=2.0.0)
Requires-Dist: flax (>=0.6.0)
Provides-Extra: testing
Requires-Dist: basicsr (>=1.4.2) ; extra == 'testing'
